[
  {
    "id": 1,
    "title": "Какой газ является основным компонентом воздуха?",
    "array": [
      { "A": "Кислород", "B": "Азот", "C": "Углекислый газ", "D": "Водород" }
    ],
    "trueAnswer": "B",
    "description": "Азот составляет около 78% объема воздуха."
  },
  {
    "id": 2,
    "title": "Сколько планет в Солнечной системе?",
    "array": [{ "A": "7", "B": "8", "C": "9", "D": "10" }],
    "trueAnswer": "B",
    "description": "В Солнечной системе 8 планет, а не 9 как раньше считали из-за исключения Плутона."
  },
  {
    "id": 3,
    "title": "Какой химический элемент имеет символ 'Fe'?",
    "array": [{ "A": "Фтор", "B": "Железо", "C": "Фосфор", "D": "Франций" }],
    "trueAnswer": "B",
    "description": "Символ 'Fe' обозначает элемент железо."
  },
  {
    "id": 4,
    "title": "Какой химический элемент имеет символ 'H'?",
    "array": [{ "A": "Гелий", "B": "Гидроген", "C": "Кислород", "D": "Хлор" }],
    "trueAnswer": "B",
    "description": "Символ 'H' обозначает элемент водород."
  },
  {
    "id": 5,
    "title": "Как называется процесс, в результате которого растения используют энергию солнечного света для создания питательных веществ?",
    "array": [
      { "A": "Фотосинтез", "B": "Дыхание", "C": "Эволюция", "D": "Конденсация" }
    ],
    "trueAnswer": "A",
    "description": "Процесс называется фотосинтезом."
  },
  {
    "id": 6,
    "title": "Какое самое большое озеро в мире?",
    "array": [
      {
        "A": "Озеро Байкал",
        "B": "Великое Озеро",
        "C": "Озеро Нил",
        "D": "Каспийское море"
      }
    ],
    "trueAnswer": "D",
    "description": "Каспийское море является самым большим озером в мире по площади."
  },
  {
    "id": 7,
    "title": "Какой город называют 'Северной столицей России'?",
    "array": [
      {
        "A": "Москва",
        "B": "Екатеринбург",
        "C": "Санкт-Петербург",
        "D": "Новосибирск"
      }
    ],
    "trueAnswer": "C",
    "description": "Санкт-Петербург называют 'Северной столицей России'."
  },
  {
    "id": 8,
    "title": "Какой химический элемент имеет символ 'O'?",
    "array": [{ "A": "Оксид", "B": "Кислород", "C": "Олово", "D": "Оберон" }],
    "trueAnswer": "B",
    "description": "Символ 'O' обозначает элемент кислород."
  },
  {
    "id": 9,
    "title": "Как называется самая длинная река в мире?",
    "array": [{ "A": "Амазонка", "B": "Нил", "C": "Янцзы", "D": "Миссисипи" }],
    "trueAnswer": "B",
    "description": "Самая длинная река в мире - Нил."
  },
  {
    "id": 10,
    "title": "Какое количество континентов на Земле?",
    "array": [{ "A": "4", "B": "5", "C": "6", "D": "7" }],
    "trueAnswer": "D",
    "description": "На Земле семь континентов."
  },

  {
    "id": 11,
    "title": "Какой химический элемент имеет символ 'H'?",
    "array": [{ "A": "Гелий", "B": "Гидроген", "C": "Кислород", "D": "Хлор" }],
    "trueAnswer": "B",
    "description": "Символ 'H' обозначает элемент водород."
  },
  {
    "id": 12,
    "title": "Как называется процесс, в результате которого растения используют энергию солнечного света для создания питательных веществ?",
    "array": [
      {
        "A": "Фотосинтез",
        "B": "Дыхание",
        "C": "Эволюция",
        "D": "Конденсация"
      }
    ],
    "trueAnswer": "A",
    "description": "Процесс называется фотосинтезом."
  },
  {
    "id": 13,
    "title": "Какое самое большое озеро в мире?",
    "array": [
      {
        "A": "Озеро Байкал",
        "B": "Великое Озеро",
        "C": "Озеро Нил",
        "D": "Каспийское море"
      }
    ],
    "trueAnswer": "D",
    "description": "Каспийское море является самым большим озером в мире по площади."
  },
  {
    "id": 14,
    "title": "Какой город называют 'Северной столицей России'?",
    "array": [
      {
        "A": "Москва",
        "B": "Екатеринбург",
        "C": "Санкт-Петербург",
        "D": "Новосибирск"
      }
    ],
    "trueAnswer": "C",
    "description": "Санкт-Петербург называют 'Северной столицей России'."
  },
  {
    "id": 15,
    "title": "Какой химический элемент имеет символ 'O'?",
    "array": [{ "A": "Оксид", "B": "Кислород", "C": "Олово", "D": "Оберон" }],
    "trueAnswer": "B",
    "description": "Символ 'O' обозначает элемент кислород."
  },
  {
    "id": 16,
    "title": "Как называется самая длинная река в мире?",
    "array": [{ "A": "Амазонка", "B": "Нил", "C": "Янцзы", "D": "Миссисипи" }],
    "trueAnswer": "B",
    "description": "Самая длинная река в мире - Нил."
  },
  {
    "id": 17,
    "title": "Какое количество континентов на Земле?",
    "array": [{ "A": "4", "B": "5", "C": "6", "D": "7" }],
    "trueAnswer": "D",
    "description": "На Земле семь континентов."
  },
  {
    "id": 18,
    "title": "Какой химический элемент обозначается как 'Na'?",
    "array": [{ "A": "Неодим", "B": "Натрий", "C": "Никель", "D": "Ниобий" }],
    "trueAnswer": "B",
    "description": "Символ 'Na' обозначает элемент натрий."
  },
  {
    "id": 19,
    "title": "Какое из этих животных не является насекомым?",
    "array": [{ "A": "Пчела", "B": "Комар", "C": "Паук", "D": "Таракан" }],
    "trueAnswer": "C",
    "description": "Паук не является насекомым, а относится к классу паукообразных."
  },
  {
    "id": 20,
    "title": "Какой химический элемент имеет символ 'C'?",
    "array": [
      { "A": "Карбонит", "B": "Калций", "C": "Углерод", "D": "Кобальт" }
    ],
    "trueAnswer": "C",
    "description": "Символ 'C' обозначает элемент углерод."
  },

  {
    "id": 21,
    "title": "Какое вещество обычно испаряется при кипении воды?",
    "array": [{ "A": "Соль", "B": "Уголь", "C": "Кислород", "D": "Аммиак" }],
    "trueAnswer": "D",
    "description": "При кипении воды обычно испаряется аммиак."
  },
  {
    "id": 22,
    "title": "Какое из этих событий произошло позже?",
    "array": [
      {
        "A": "Первая мировая война",
        "B": "Открытие Америки",
        "C": "Создание Интернета",
        "D": "Падение Римской империи"
      }
    ],
    "trueAnswer": "A",
    "description": "Первая мировая война произошла позже остальных событий."
  },
  {
    "id": 23,
    "title": "Какая планета в Солнечной системе известна своим кольцом?",
    "array": [{ "A": "Марс", "B": "Юпитер", "C": "Сатурн", "D": "Уран" }],
    "trueAnswer": "C",
    "description": "Сатурн известен своими кольцами."
  },
  {
    "id": 24,
    "title": "Какой газ используется растениями для фотосинтеза?",
    "array": [
      { "A": "Кислород", "B": "Водород", "C": "Углекислый газ", "D": "Азот" }
    ],
    "trueAnswer": "C",
    "description": "Растения используют углекислый газ для фотосинтеза."
  },
  {
    "id": 25,
    "title": "Какое из этих животных способно летать?",
    "array": [
      { "A": "Кенгуру", "B": "Слон", "C": "Акула", "D": "Летучая мышь" }
    ],
    "trueAnswer": "D",
    "description": "Летучая мышь способна летать."
  },
  {
    "id": 26,
    "title": "Какое из следующих чисел является простым?",
    "array": [{ "A": "10", "B": "15", "C": "20", "D": "23" }],
    "trueAnswer": "D",
    "description": "Число 23 является простым числом."
  },
  {
    "id": 27,
    "title": "Какой химический элемент используется для создания ядерной энергии?",
    "array": [{ "A": "Ртуть", "B": "Уран", "C": "Свинец", "D": "Серебро" }],
    "trueAnswer": "B",
    "description": "Уран используется для создания ядерной энергии."
  },
  {
    "id": 28,
    "title": "Как называется научное изучение организмов и их взаимодействия с окружающей средой?",
    "array": [
      { "A": "Геология", "B": "Астрономия", "C": "Биология", "D": "Экология" }
    ],
    "trueAnswer": "D",
    "description": "Научное изучение организмов и их взаимодействия с окружающей средой называется экологией."
  },
  {
    "id": 29,
    "title": "Какой химический элемент обозначается как 'K'?",
    "array": [{ "A": "Калций", "B": "Криптон", "C": "Калий", "D": "Кураре" }],
    "trueAnswer": "C",
    "description": "Символ 'K' обозначает элемент калий."
  },
  {
    "id": 30,
    "title": "Как называется единица измерения силы тока?",
    "array": [{ "A": "Вольт", "B": "Ватт", "C": "Ампер", "D": "Ом" }],
    "trueAnswer": "C",
    "description": "Единица измерения силы тока - ампер."
  }
]
